buttplug/__init__.py
buttplug/client/__init__.py
buttplug/client/client.py
buttplug/client/connector.py
buttplug/client/websocket_connector.py
buttplug/core/__init__.py
buttplug/core/enums.py
buttplug/core/errors.py
buttplug/core/messages.py
buttplug/utils/__init__.py
buttplug/utils/eventhandler.py
buttplug-0.2.1.dist-info/LICENSE
buttplug-0.2.1.dist-info/METADATA
buttplug-0.2.1.dist-info/WHEEL
buttplug-0.2.1.dist-info/top_level.txt
buttplug-0.2.1.dist-info/RECORD
