Metadata-Version: 2.1
Name: buttplug
Version: 0.2.1
Summary: Python implementation of the Buttplug Intimate Hardware Control Protocol.
Home-page: https://github.com/buttplugio/buttplug-py
Author: Nonpolynomial
Author-email: kyle@nonpolynomial.com
License: UNKNOWN
Platform: UNKNOWN
Classifier: Programming Language :: Python :: 3.7
Classifier: Programming Language :: Python :: 3.8
Classifier: Programming Language :: Python :: 3.9
Classifier: Development Status :: 4 - Beta
Classifier: License :: OSI Approved :: BSD License
Classifier: Operating System :: OS Independent
Requires-Dist: websockets (>=10)
